pylsqpack-0.3.21.dist-info/RECORD
pylsqpack-0.3.21.dist-info/WHEEL
pylsqpack-0.3.21.dist-info/top_level.txt
pylsqpack-0.3.21.dist-info/METADATA
pylsqpack-0.3.21.dist-info/licenses/LICENSE
pylsqpack/__init__.pyi
pylsqpack/binding.c
pylsqpack/__init__.py
pylsqpack/py.typed
pylsqpack/_binding.abi3.so
