Metadata-Version: 2.4
Name: pylsqpack
Version: 0.3.21
Summary: Python wrapper for the ls-qpack QPACK library
Author-email: Jeremy Lainé <jeremy.laine@m4x.org>
License-Expression: BSD-3-Clause
Project-URL: homepage, https://github.com/aiortc/pylsqpack
Project-URL: documentation, https://pylsqpack.readthedocs.io/
Classifier: Development Status :: 5 - Production/Stable
Classifier: Environment :: Web Environment
Classifier: Intended Audience :: Developers
Classifier: Operating System :: OS Independent
Classifier: Programming Language :: Python
Classifier: Programming Language :: Python :: 3
Classifier: Programming Language :: Python :: 3.9
Classifier: Programming Language :: Python :: 3.10
Classifier: Programming Language :: Python :: 3.11
Classifier: Programming Language :: Python :: 3.12
Classifier: Programming Language :: Python :: 3.13
Classifier: Topic :: Internet :: WWW/HTTP
Requires-Python: >=3.9
License-File: LICENSE
Dynamic: license-file
